fastapi_restful/__init__.py
fastapi_restful/api.py
fastapi_restful/resource.py
fastapi_restful/utils.py
fastapi_restful_extension-0.4.2.dist-info/LICENSE
fastapi_restful_extension-0.4.2.dist-info/WHEEL
fastapi_restful_extension-0.4.2.dist-info/METADATA
fastapi_restful_extension-0.4.2.dist-info/RECORD
