Metadata-Version: 2.1
Name: fastapi-restful-extension
Version: 0.4.2
Summary: Extension for make RESTful interfaces with FastAPI.
License: MIT
Keywords: fastapi,api,rest-api,async
Author: Shumilo Maksim
Author-email: shumilo.mk@gmail.com
Requires-Python: >=3.7,<4.0
Classifier: Environment :: Web Environment
Classifier: Framework :: AsyncIO
Classifier: Framework :: FastAPI
Classifier: Intended Audience :: Developers
Classifier: Intended Audience :: Information Technology
Classifier: License :: OSI Approved :: MIT License
Classifier: Operating System :: OS Independent
Classifier: Programming Language :: Python :: 3
Classifier: Programming Language :: Python :: 3.7
Classifier: Programming Language :: Python :: 3.8
Classifier: Programming Language :: Python :: 3.9
Classifier: Programming Language :: Python :: 3.10
Classifier: Programming Language :: Python :: 3.11
Classifier: Programming Language :: Python :: 3.10
Classifier: Programming Language :: Python :: 3.7
Classifier: Programming Language :: Python :: 3.8
Classifier: Programming Language :: Python :: 3.9
Classifier: Topic :: Internet
Classifier: Topic :: Internet :: WWW/HTTP
Classifier: Topic :: Internet :: WWW/HTTP :: HTTP Servers
Classifier: Topic :: Software Development
Classifier: Topic :: Software Development :: Libraries
Classifier: Topic :: Software Development :: Libraries :: Python Modules
Requires-Dist: fastapi (>=0.78.0)
Project-URL: Documentation, https://maximshumilo.github.io/fastapi-restful-extension/
Project-URL: Homepage, https://github.com/maximshumilo/fastapi-restful-extension
Project-URL: Repository, https://github.com/maximshumilo/fastapi-restful-extension
